LICENSE
README.md
setup.cfg
setup.py
ilikepaintings/__init__.py
ilikepaintings/predictor.py
ilikepaintings.egg-info/PKG-INFO
ilikepaintings.egg-info/SOURCES.txt
ilikepaintings.egg-info/dependency_links.txt
ilikepaintings.egg-info/requires.txt
ilikepaintings.egg-info/top_level.txt
ilikepaintings/weights/Sidhu/RN101.pth
ilikepaintings/weights/Sidhu/RN50.pth
ilikepaintings/weights/Sidhu/RN50x16.pth
ilikepaintings/weights/Sidhu/RN50x4.pth
ilikepaintings/weights/Sidhu/RN50x64.pth
ilikepaintings/weights/Sidhu/ViT-B-16.pth
ilikepaintings/weights/Sidhu/ViT-B-32.pth
ilikepaintings/weights/Sidhu/ViT-L-14.pth
ilikepaintings/weights/Sidhu/ViT-L-14@336px.pth
ilikepaintings/weights/VAPS999/RN101.pth
ilikepaintings/weights/VAPS999/RN50.pth
ilikepaintings/weights/VAPS999/RN50x16.pth
ilikepaintings/weights/VAPS999/RN50x4.pth
ilikepaintings/weights/VAPS999/RN50x64.pth
ilikepaintings/weights/VAPS999/ViT-B-16.pth
ilikepaintings/weights/VAPS999/ViT-B-32.pth
ilikepaintings/weights/VAPS999/ViT-L-14.pth
ilikepaintings/weights/VAPS999/ViT-L-14@336px.pth